datasette_preact/__init__.py
datasette_preact/static/preact-10.27.2-htm-3.1.1.min.js
datasette_preact/templates/datasette-preact.html
datasette_preact-0.0.1.dist-info/licenses/LICENSE
examples/sample.py
tests/test_preact.py
datasette_preact-0.0.1.dist-info/METADATA
datasette_preact-0.0.1.dist-info/WHEEL
datasette_preact-0.0.1.dist-info/entry_points.txt
datasette_preact-0.0.1.dist-info/top_level.txt
datasette_preact-0.0.1.dist-info/RECORD
