Metadata-Version: 2.4
Name: datasette-preact
Version: 0.0.1
Summary: Pre-bundled Preact for easy interactive JS Datasette plugins
Author: Alex Garcia
License-Expression: Apache-2.0
Project-URL: Homepage, https://github.com/datasette/datasette-preact
Project-URL: Changelog, https://github.com/datasette/datasette-preact/releases
Project-URL: Issues, https://github.com/datasette/datasette-preact/issues
Project-URL: CI, https://github.com/datasette/datasette-preact/actions
Classifier: Framework :: Datasette
Requires-Python: >=3.9
License-File: LICENSE
Requires-Dist: datasette
Provides-Extra: test
Requires-Dist: pytest; extra == "test"
Requires-Dist: pytest-asyncio; extra == "test"
Dynamic: license-file
